ptth/__init__.py
ptth/api.py
ptth/forte_names.py
post_tonal_theory_helper_mbmasuda-0.1.1.dist-info/LICENSE
post_tonal_theory_helper_mbmasuda-0.1.1.dist-info/METADATA
post_tonal_theory_helper_mbmasuda-0.1.1.dist-info/WHEEL
post_tonal_theory_helper_mbmasuda-0.1.1.dist-info/top_level.txt
post_tonal_theory_helper_mbmasuda-0.1.1.dist-info/RECORD
