Metadata-Version: 2.1
Name: post-tonal-theory-helper-mbmasuda
Version: 0.1.1
Summary: Post-tonal music theory analysis functions
Home-page: https://github.com/mbmasuda/post-tonal-theory-helper
Author: Mari Masuda
Author-email: mbmasuda.github@gmail.com
License: UNKNOWN
Platform: UNKNOWN
Classifier: Programming Language :: Python :: 3
Classifier: License :: OSI Approved :: MIT License
Classifier: Operating System :: OS Independent
